enumeratiam/__init__.py
enumeratiam/getclient.py
enumeratiam-0.0.4.dist-info/METADATA
enumeratiam-0.0.4.dist-info/WHEEL
enumeratiam-0.0.4.dist-info/top_level.txt
enumeratiam-0.0.4.dist-info/RECORD
